isnt_that_odd/__init__.py
isnt_that_odd/cli.py
isnt_that_odd/core.py
isnt_that_odd/prompts/__init__.py
isnt_that_odd/prompts/even_odd.txt
isnt_that_odd-0.1.2.dist-info/METADATA
isnt_that_odd-0.1.2.dist-info/WHEEL
isnt_that_odd-0.1.2.dist-info/entry_points.txt
isnt_that_odd-0.1.2.dist-info/licenses/LICENSE
isnt_that_odd-0.1.2.dist-info/RECORD
