Metadata-Version: 2.4
Name: isnt_that_odd
Version: 0.1.2
Summary: A Python library that determines if a number is even using LLM APIs
Project-URL: Homepage, https://github.com/LaunchPlatform/isnt_that_odd
Project-URL: Repository, https://github.com/LaunchPlatform/isnt_that_odd.git
Project-URL: Issues, https://github.com/LaunchPlatform/isnt_that_odd/issues
Author-email: Fang-Pen Lin <hello@fangpenlin.com>
License: MIT License
License-File: LICENSE
Classifier: Development Status :: 3 - Alpha
Classifier: Intended Audience :: Developers
Classifier: License :: OSI Approved :: MIT License
Classifier: Programming Language :: Python :: 3
Classifier: Programming Language :: Python :: 3.8
Classifier: Programming Language :: Python :: 3.9
Classifier: Programming Language :: Python :: 3.10
Classifier: Programming Language :: Python :: 3.11
Classifier: Programming Language :: Python :: 3.12
Requires-Python: >=3.8
Requires-Dist: click>=8.0.0
Requires-Dist: jinja2>=3.0.0
Requires-Dist: litellm>=1.0.0
Requires-Dist: pydantic>=2.0.0
